Workbook

Sheet Driver Inputs
A1: Startup Financial Model - General Inputs
B4: Starting Cash Balance | C4: 500000
B5: Monthly Salary per Engineer | C5: 8000
B6: Marketing Multiplier | C6: 1
B9: Select Active Scenario: | C9: Hire 2 Engineers

Sheet Financial Forecast
A3: Financial Timeline | B3: Month 1 | C3: Month 2 | D3: Month 3 | E3: Month 4 | F3: Month 5 | G3: Month 6 | H3: Month 7 | I3: Month 8 | J3: Month 9 | K3: Month 10 | L3: Month 11 | M3: Month 12
A4: Beginning Cash Balance | B4: ='Driver Inputs'!C4 -> 500000 | C4: =B13 -> 480000 | D4: =C13 -> 460000 | E4: =D13 -> 440000 | F4: =E13 -> 420000 | G4: =F13 -> 400000 | H4: =G13 -> 380000 | I4: =H13 -> 360000 | J4: =I13 -> 340000 | ... M4: =L13 -> 280000
A5: Total Revenue | B5: 15000 | C5: 15000 | D5: 15000 | E5: 15000 | F5: 15000 | G5: 15000 | H5: 15000 | I5: 15000 | J5: 15000 | K5: 15000 | L5: 15000 | M5: 15000
A6: Expenses:
A7: Salaries | B7: =25000 + IF('Driver Inputs'!$B$9="Hire 2 Engineers", 2 * 'Driver Inputs'!$B$5, 0) -> 25000 | C7: =25000 + IF('Driver Inputs'!$B$9="Hire 2 Engineers", 2 * 'Driver Inputs'!$B$5, 0) -> 25000 | D7: =25000 + IF('Driver Inputs'!$B$9="Hire 2 Engineers", 2 * 'Driver Inputs'!$B$5, 0) -> 25000 | E7: =25000 + IF('Driver Inputs'!$B$9="Hire 2 Engineers", 2 * 'Driver Inputs'!$B$5, 0) -> 25000 | F7: =25000 + IF('Driver Inputs'!$B$9="Hire 2 Engineers", 2 * 'Driver Inputs'!$B$5, 0) -> 25000 | G7: =25000 + IF('Driver Inputs'!$B$9="Hire 2 Engineers", 2 * 'Driver Inputs'!$B$5, 0) -> 25000 | H7: =25000 + IF('Driver Inputs'!$B$9="Hire 2 Engineers", 2 * 'Driver Inputs'!$B$5, 0) -> 25000 | I7: =25000 + IF('Driver Inputs'!$B$9="Hire 2 Engineers", 2 * 'Driver Inputs'!$B$5, 0) -> 25000 | ... M7: =25000 + IF('Driver Inputs'!$B$9="Hire 2 Engineers", 2 * 'Driver Inputs'!$B$5, 0) -> 25000
A8: Marketing | B8: =5000 * IF('Driver Inputs'!$B$9="Double Marketing", 2, 1) -> 5000 | C8: =5000 * IF('Driver Inputs'!$B$9="Double Marketing", 2, 1) -> 5000 | D8: =5000 * IF('Driver Inputs'!$B$9="Double Marketing", 2, 1) -> 5000 | E8: =5000 * IF('Driver Inputs'!$B$9="Double Marketing", 2, 1) -> 5000 | F8: =5000 * IF('Driver Inputs'!$B$9="Double Marketing", 2, 1) -> 5000 | G8: =5000 * IF('Driver Inputs'!$B$9="Double Marketing", 2, 1) -> 5000 | H8: =5000 * IF('Driver Inputs'!$B$9="Double Marketing", 2, 1) -> 5000 | I8: =5000 * IF('Driver Inputs'!$B$9="Double Marketing", 2, 1) -> 5000 | ... M8: =5000 * IF('Driver Inputs'!$B$9="Double Marketing", 2, 1) -> 5000
A9: Tech Stack | B9: 2000 | C9: 2000 | D9: 2000 | E9: 2000 | F9: 2000 | G9: 2000 | H9: 2000 | I9: 2000 | J9: 2000 | K9: 2000 | L9: 2000 | M9: 2000
A10: Rent & Admin | B10: 3000 | C10: 3000 | D10: 3000 | E10: 3000 | F10: 3000 | G10: 3000 | H10: 3000 | I10: 3000 | J10: 3000 | K10: 3000 | L10: 3000 | M10: 3000
A11: Gross Burn | B11: =SUM(B7:B10) -> 35000 | C11: =SUM(C7:C10) -> 35000 | D11: =SUM(D7:D10) -> 35000 | E11: =SUM(E7:E10) -> 35000 | F11: =SUM(F7:F10) -> 35000 | G11: =SUM(G7:G10) -> 35000 | H11: =SUM(H7:H10) -> 35000 | I11: =SUM(I7:I10) -> 35000 | ... M11: =SUM(M7:M10) -> 35000
A12: Net Burn | B12: =B11-B5 -> 20000 | C12: =C11-C5 -> 20000 | D12: =D11-D5 -> 20000 | E12: =E11-E5 -> 20000 | F12: =F11-F5 -> 20000 | G12: =G11-G5 -> 20000 | H12: =H11-H5 -> 20000 | I12: =I11-I5 -> 20000 | ... M12: =M11-M5 -> 20000
A13: Ending Cash Balance | B13: =B4-B12 -> 480000 | C13: =C4-C12 -> 460000 | D13: =D4-D12 -> 440000 | E13: =E4-E12 -> 420000 | F13: =F4-F12 -> 400000 | G13: =G4-G12 -> 380000 | H13: =H4-H12 -> 360000 | I13: =I4-I12 -> 340000 | ... M13: =M4-M12 -> 260000
A14: Runway (Months) | B14: =IF(B12<=0, 99, B4/B12) -> 25 | C14: =IF(C12<=0, 99, C4/C12) -> 24 | D14: =IF(D12<=0, 99, D4/D12) -> 23 | E14: =IF(E12<=0, 99, E4/E12) -> 22 | F14: =IF(F12<=0, 99, F4/F12) -> 21 | G14: =IF(G12<=0, 99, G4/G12) -> 20 | H14: =IF(H12<=0, 99, H4/H12) -> 19 | I14: =IF(I12<=0, 99, I4/I12) -> 18 | ... M14: =IF(M12<=0, 99, M4/M12) -> 14

Sheet Dashboard
C1: STARTUP CASH RUNWAY & BURN RATE PREDICTOR
A3: CURRENT RUNWAY (MONTHS) | B3: ='Financial Forecast'!B14 -> 25
A5: CURRENT CASH BALANCE | B5: 500000
A7: AVG. MONTHLY NET BURN | B7: =AVERAGE('Financial Forecast'!B12:M12) -> 20000
B24: Select Active Scenario: | C24: Double Marketing
